django_google_maps/__init__.py
django_google_maps/fields.py
django_google_maps/models.py
django_google_maps/widgets.py
django_google_maps/static/django_google_maps/css/google-maps-admin.css
django_google_maps/static/django_google_maps/js/google-maps-admin.js
django_google_maps/templates/django_google_maps/widgets/map_widget.html
django_google_maps-0.13.0.dist-info/LICENSE
django_google_maps-0.13.0.dist-info/METADATA
django_google_maps-0.13.0.dist-info/WHEEL
django_google_maps-0.13.0.dist-info/top_level.txt
django_google_maps-0.13.0.dist-info/RECORD
